geci_pipa/__init__.py
geci_pipa/repo_init.py
geci_pipa-0.1.1.dist-info/LICENSE
geci_pipa-0.1.1.dist-info/WHEEL
geci_pipa-0.1.1.dist-info/METADATA
geci_pipa-0.1.1.dist-info/RECORD
