Metadata-Version: 2.1
Name: geci_pipa
Version: 0.1.1
Summary: Internal platforms for analysts module
Home-page: https://github.com/IslasGECI/pipa
Author: Ciencia de Datos • GECI
Author-email: ciencia.datos@islas.org.mx
Requires-Python: >=3.9
Classifier: License :: OSI Approved :: GNU General Public License v3 or later (GPLv3+)
